[{
    "text": "All", 
    "expanded": true, 
    "id": 0, 
    "items": [
        {
            "text": "Apple", 
            "expanded": true, 
            "pid": 0, 
            "comments": "20140821-1", 
            "items": [
                {
                    "text": "After", 
                    "expanded": true, 
                    "pid": 1, 
                    "comments": "20140821-7", 
                    "items": [], 
                    "id": 7
                }
            ], 
            "id": 1
        }, 
        {
            "text": "Banana", 
            "expanded": true, 
            "pid": 0, 
            "comments": "20140821-2", 
            "items": [], 
            "id": 2
        }, 
        {
            "text": "Change", 
            "expanded": true, 
            "pid": 0, 
            "comments": "20140821-3", 
            "items": [], 
            "id": 3
        }, 
        {
            "text": "\u7814\u53d1\u90e8", 
            "expanded": true, 
            "pid": 0, 
            "comments": "20140821-4", 
            "items": [
                {
                    "text": "\u5f00\u53d1\u7ec4", 
                    "expanded": true, 
                    "pid": 4, 
                    "comments": "20140821-8", 
                    "items": [], 
                    "id": 8
                }, 
                {
                    "text": "\u6d4b\u8bd5\u7ec4", 
                    "expanded": true, 
                    "pid": 4, 
                    "comments": "20140821-9", 
                    "items": [], 
                    "id": 9
                }
            ], 
            "id": 4
        }, 
        {
            "text": "\u8fd0\u7ef4\u90e8", 
            "expanded": true, 
            "pid": 0, 
            "comments": "20140821-5", 
            "items": [], 
            "id": 5
        }, 
        {
            "text": "\u9500\u552e\u90e8", 
            "expanded": true, 
            "pid": 0, 
            "comments": "20140821-6", 
            "items": [
                {
                    "text": "\u552e\u524d\u7ec4", 
                    "expanded": true, 
                    "pid": 6, 
                    "comments": "20140821-10", 
                    "items": [], 
                    "id": 10
                }, 
                {
                    "text": "\u552e\u540e\u7ec4", 
                    "expanded": true, 
                    "pid": 6, 
                    "comments": "20140821-11", 
                    "items": [], 
                    "id": 11
                }
            ], 
            "id": 6
        }
    ]
}]